MANIFEST.in
README.txt
setup.py
c2/__init__.py
c2.patch.contentpaste.egg-info/PKG-INFO
c2.patch.contentpaste.egg-info/SOURCES.txt
c2.patch.contentpaste.egg-info/dependency_links.txt
c2.patch.contentpaste.egg-info/entry_points.txt
c2.patch.contentpaste.egg-info/namespace_packages.txt
c2.patch.contentpaste.egg-info/not-zip-safe
c2.patch.contentpaste.egg-info/requires.txt
c2.patch.contentpaste.egg-info/top_level.txt
c2/patch/__init__.py
c2/patch/contentpaste/__init__.py
c2/patch/contentpaste/configure.zcml
c2/patch/contentpaste/version.txt
c2/patch/contentpaste/browser/__init__.py
c2/patch/contentpaste/browser/configure.zcml
c2/patch/contentpaste/browser/paste.py
c2/patch/contentpaste/controlpanel/__init__.py
c2/patch/contentpaste/controlpanel/configure.zcml
c2/patch/contentpaste/controlpanel/interfaces.py
c2/patch/contentpaste/controlpanel/main.py
c2/patch/contentpaste/locales/c2.patch.contentpaste.pot
c2/patch/contentpaste/locales/en/LC_MESSAGES/c2.patch.contentpaste.mo
c2/patch/contentpaste/locales/en/LC_MESSAGES/c2.patch.contentpaste.po
c2/patch/contentpaste/locales/ja/LC_MESSAGES/c2.patch.contentpaste.mo
c2/patch/contentpaste/locales/ja/LC_MESSAGES/c2.patch.contentpaste.po
c2/patch/contentpaste/profiles/default/actions.xml
c2/patch/contentpaste/profiles/default/controlpanel.xml
c2/patch/contentpaste/profiles/default/metadata.xml
c2/patch/contentpaste/profiles/default/registry.xml
c2/patch/contentpaste/tests/__init__.py
c2/patch/contentpaste/tests/test_paste.py
c2/patch/contentpaste/tests/test_setup.py
docs/HISTORY.txt
docs/INSTALL.txt
docs/LICENSE.GPL
docs/LICENSE.txt