Metadata-Version: 1.1
Name: c2.patch.contentpaste
Version: 1.0b4
Summary: This product is supsupported Duplicate Content for plone, not objcet paste
Home-page: http://www.cmscom.jp
Author: Manabu TERADA
Author-email: terada@cmscom.jp
License: GPL
Keywords: plone copy paste patch
Platform: UNKNOWN
Classifier: Framework :: Plone
Classifier: Programming Language :: Python
